confuse/__init__.py
confuse/core.py
confuse/exceptions.py
confuse/sources.py
confuse/templates.py
confuse/util.py
confuse/yaml_util.py
confuse-1.7.0.dist-info/LICENSE
confuse-1.7.0.dist-info/WHEEL
confuse-1.7.0.dist-info/METADATA
confuse-1.7.0.dist-info/RECORD
